hypothesis_010/__init__.py
hypothesis_010/py.typed
hypothesis_010-0.0.1.dist-info/LICENSE
hypothesis_010-0.0.1.dist-info/METADATA
hypothesis_010-0.0.1.dist-info/WHEEL
hypothesis_010-0.0.1.dist-info/top_level.txt
hypothesis_010-0.0.1.dist-info/RECORD
