Metadata-Version: 2.1
Name: hypothesis-010
Version: 0.0.1
Summary: Generate test data from 010-Editor binary templates with Hypothesis
Home-page: https://github.com/Zac-HD/hypothesis-010
Author: Zac Hatfield-Dodds
Author-email: zac@hypothesis.works
License: MPL 2.0
Project-URL: Funding, https://github.com/sponsors/Zac-HD
Keywords: python testing fuzzing property-based-testing 010editor
Platform: UNKNOWN
Classifier: Development Status :: 1 - Planning
Classifier: Framework :: Hypothesis
Classifier: Intended Audience :: Developers
Classifier: License :: OSI Approved :: Mozilla Public License 2.0 (MPL 2.0)
Classifier: Programming Language :: Python
Classifier: Programming Language :: Python :: 3
Classifier: Programming Language :: Python :: 3.6
Classifier: Programming Language :: Python :: 3.7
Classifier: Programming Language :: Python :: 3.8
Classifier: Topic :: Software Development :: Testing
Classifier: Typing :: Typed
Requires-Python: >=3.6
Requires-Dist: hypothesis (>=5.36.0)
Requires-Dist: py010parser (>=0.1.18)
